halerror/__init__.py
halerror-0.4.1.dist-info/LICENSE
halerror-0.4.1.dist-info/METADATA
halerror-0.4.1.dist-info/WHEEL
halerror-0.4.1.dist-info/top_level.txt
halerror-0.4.1.dist-info/RECORD
