Metadata-Version: 2.1
Name: halerror
Version: 0.4.1
Summary: The best python exception library!
Home-page: https://github.com/jmp1985/halerror
Author: James Parkhurst
Author-email: james.parkhurst@diamond.ac.uk
License: BSD license
Project-URL: Source, https://github.com/jmp1985/halerror
Project-URL: Tracker, https://github.com/jmp1985/halerror/issues
Keywords: exception,HAL-9000
Platform: unix
Platform: linux
Platform: osx
Platform: cygwin
Platform: win32
Classifier: Development Status :: 4 - Beta
Classifier: Intended Audience :: Developers
Classifier: License :: OSI Approved :: BSD License
Classifier: Operating System :: POSIX
Classifier: Operating System :: Microsoft :: Windows
Classifier: Operating System :: MacOS :: MacOS X
Classifier: Topic :: Utilities
Classifier: Programming Language :: Python :: 3.4
Classifier: Programming Language :: Python :: 3.5
Classifier: Programming Language :: Python :: 3.6
Provides-Extra: build_sphinx
Requires-Dist: sphinx ; extra == 'build_sphinx'
Requires-Dist: sphinx-rtd-theme ; extra == 'build_sphinx'
